aries_basic_controller/__init__.py
aries_basic_controller/aries_controller.py
aries_basic_controller/controllers/__init__.py
aries_basic_controller/controllers/action_menu.py
aries_basic_controller/controllers/base.py
aries_basic_controller/controllers/connections.py
aries_basic_controller/controllers/credential.py
aries_basic_controller/controllers/definitions.py
aries_basic_controller/controllers/issuer.py
aries_basic_controller/controllers/ledger.py
aries_basic_controller/controllers/mediation.py
aries_basic_controller/controllers/messaging.py
aries_basic_controller/controllers/multitenant.py
aries_basic_controller/controllers/oob.py
aries_basic_controller/controllers/proof.py
aries_basic_controller/controllers/revocation.py
aries_basic_controller/controllers/schema.py
aries_basic_controller/controllers/server.py
aries_basic_controller/controllers/wallet.py
aries_basic_controller/helpers/__init__.py
aries_basic_controller/helpers/utils.py
aries_basic_controller/models/__init__.py
aries_basic_controller/models/connection.py
aries_basic_controller/models/errors.py
aries_basic_controller-0.3.dist-info/LICENSE
aries_basic_controller-0.3.dist-info/METADATA
aries_basic_controller-0.3.dist-info/WHEEL
aries_basic_controller-0.3.dist-info/top_level.txt
aries_basic_controller-0.3.dist-info/RECORD
